{
  "species": 22557,
  "subspecies": 172,
  "genera": 5082,
  "families": 7118,
  "orders": 1207,
  "classes": 312,
  "phyla": 119,
  "kingdoms": 9,
  "genus": 5082,
  "family": 7118,
  "order": 1207,
  "class": 312,
  "phylum": 119,
  "kingdom": 9,
  "rank_counts": {
    "class": 175,
    "family": 7195,
    "forma": 1,
    "genus": 4972,
    "kingdom": 10,
    "order": 831,
    "phylum": 51,
    "species": 22557,
    "subspecies": 172,
    "unranked": 427
  },
  "records_archived": 43383,
  "source_assertions": 43387,
  "synonyms": 6968,
  "unresolved_conflicts": 1,
  "volumes": 1,
  "last_updated": "2026-07-23T19:49:01Z",
  "count_method": "local-deduplicated-append-only-canonical-corpus"
}
