{
  "species": 20878,
  "subspecies": 158,
  "genera": 4722,
  "families": 7113,
  "orders": 1207,
  "classes": 312,
  "phyla": 119,
  "kingdoms": 9,
  "genus": 4722,
  "family": 7113,
  "order": 1207,
  "class": 312,
  "phylum": 119,
  "kingdom": 9,
  "rank_counts": {
    "class": 175,
    "family": 7195,
    "forma": 1,
    "genus": 4624,
    "kingdom": 10,
    "order": 830,
    "phylum": 51,
    "species": 20878,
    "subspecies": 158,
    "unranked": 369
  },
  "records_archived": 40200,
  "source_assertions": 40203,
  "synonyms": 5891,
  "unresolved_conflicts": 1,
  "volumes": 1,
  "last_updated": "2026-07-23T09:06:58Z",
  "count_method": "local-deduplicated-append-only-canonical-corpus"
}
